setup.cfg
setup.py
mdct/__init__.py
mdct/windows.py
mdct.egg-info/PKG-INFO
mdct.egg-info/SOURCES.txt
mdct.egg-info/dependency_links.txt
mdct.egg-info/requires.txt
mdct.egg-info/top_level.txt
mdct.egg-info/zip-safe
mdct/fast/__init__.py
mdct/fast/transforms.py
mdct/slow/__init__.py
mdct/slow/transforms.py