Metadata-Version: 1.1
Name: mdct
Version: 0.4
Summary: A fast MDCT implementation using SciPy and FFTs
Home-page: http://mdct.readthedocs.io/
Author: Nils Werner
Author-email: nils.werner@gmail.com
License: MIT
Platform: UNKNOWN
Classifier: Development Status :: 4 - Beta
Classifier: Intended Audience :: Telecommunications Industry
Classifier: Intended Audience :: Science/Research
Classifier: License :: OSI Approved :: MIT License
Classifier: Programming Language :: Python :: 2.7
Classifier: Programming Language :: Python :: 3
Classifier: Topic :: Multimedia :: Sound/Audio :: Analysis
Classifier: Topic :: Multimedia :: Sound/Audio :: Sound Synthesis
